LICENSE
MANIFEST.in
README.rst
setup.py
django_mptt_autocomplete.egg-info/PKG-INFO
django_mptt_autocomplete.egg-info/SOURCES.txt
django_mptt_autocomplete.egg-info/dependency_links.txt
django_mptt_autocomplete.egg-info/pbr.json
django_mptt_autocomplete.egg-info/requires.txt
django_mptt_autocomplete.egg-info/top_level.txt
mptt_autocomplete/__init__.py
mptt_autocomplete/models.py
mptt_autocomplete/tests.py
mptt_autocomplete/widgets.py
mptt_autocomplete/static/fancytree/fancytree.filter.js
mptt_autocomplete/static/fancytree/jquery-ui.min.js
mptt_autocomplete/static/fancytree/jquery.fancytree-all.js
mptt_autocomplete/static/fancytree/jquery.fancytree-all.min.js
mptt_autocomplete/static/fancytree/jquery.fancytree.min.js
mptt_autocomplete/static/fancytree/skin-awesome/ui.fancytree.css
mptt_autocomplete/static/fancytree/skin-awesome/ui.fancytree.min.css
mptt_autocomplete/static/fancytree/skin-bootstrap/ui.fancytree.css
mptt_autocomplete/static/fancytree/skin-bootstrap/ui.fancytree.min.css
mptt_autocomplete/static/fancytree/skin-bootstrap-n/ui.fancytree.css
mptt_autocomplete/static/fancytree/skin-bootstrap-n/ui.fancytree.min.css
mptt_autocomplete/static/fancytree/skin-lion/icons.gif
mptt_autocomplete/static/fancytree/skin-lion/loading.gif
mptt_autocomplete/static/fancytree/skin-lion/ui.fancytree.css
mptt_autocomplete/static/fancytree/skin-lion/ui.fancytree.min.css
mptt_autocomplete/static/fancytree/skin-themeroller/icons.gif
mptt_autocomplete/static/fancytree/skin-themeroller/loading.gif
mptt_autocomplete/static/fancytree/skin-themeroller/ui.fancytree.css
mptt_autocomplete/static/fancytree/skin-themeroller/ui.fancytree.min.css
mptt_autocomplete/static/fancytree/skin-vista/icons.gif
mptt_autocomplete/static/fancytree/skin-vista/loading.gif
mptt_autocomplete/static/fancytree/skin-vista/ui.fancytree.css
mptt_autocomplete/static/fancytree/skin-vista/ui.fancytree.min.css
mptt_autocomplete/static/fancytree/skin-win7/icons.gif
mptt_autocomplete/static/fancytree/skin-win7/loading.gif
mptt_autocomplete/static/fancytree/skin-win7/ui.fancytree.css
mptt_autocomplete/static/fancytree/skin-win7/ui.fancytree.min.css
mptt_autocomplete/static/fancytree/skin-win8/icons.gif
mptt_autocomplete/static/fancytree/skin-win8/loading.gif
