Metadata-Version: 1.1
Name: django-mptt-autocomplete
Version: 0.1.2
Summary: Django mptt widget that uses Fancytree to search and display tree data
Home-page: UNKNOWN
Author: Ajeet Lakhani, Ashish Gupta
Author-email: ajeet.lakhani@hotmail.com
License: UNKNOWN
Keywords: django,fancytree,mptt,tree
Platform: UNKNOWN
Classifier: Programming Language :: Python
Classifier: Intended Audience :: Developers
Classifier: License :: OSI Approved :: BSD License
Classifier: Operating System :: OS Independent
Classifier: Environment :: Web Environment
Classifier: Framework :: Django
Classifier: Topic :: Software Development :: Libraries :: Application Frameworks
